odoo10_addon_account_invoice_inter_company-10.0.1.1.1-nspkg.pth
odoo/addons/account_invoice_inter_company/README.rst
odoo/addons/account_invoice_inter_company/__init__.py
odoo/addons/account_invoice_inter_company/__manifest__.py
odoo/addons/account_invoice_inter_company/demo/inter_company_invoice.xml
odoo/addons/account_invoice_inter_company/i18n/account_invoice_inter_company.pot
odoo/addons/account_invoice_inter_company/i18n/es.po
odoo/addons/account_invoice_inter_company/i18n/fr.po
odoo/addons/account_invoice_inter_company/i18n/hr.po
odoo/addons/account_invoice_inter_company/i18n/nl_NL.po
odoo/addons/account_invoice_inter_company/i18n/pt.po
odoo/addons/account_invoice_inter_company/models/__init__.py
odoo/addons/account_invoice_inter_company/models/account_invoice.py
odoo/addons/account_invoice_inter_company/models/res_company.py
odoo/addons/account_invoice_inter_company/models/res_config.py
odoo/addons/account_invoice_inter_company/static/description/icon.png
odoo/addons/account_invoice_inter_company/tests/__init__.py
odoo/addons/account_invoice_inter_company/tests/test_inter_company_invoice.py
odoo/addons/account_invoice_inter_company/views/res_company_view.xml
odoo/addons/account_invoice_inter_company/views/res_config_view.xml
odoo10_addon_account_invoice_inter_company-10.0.1.1.1.dist-info/METADATA
odoo10_addon_account_invoice_inter_company-10.0.1.1.1.dist-info/WHEEL
odoo10_addon_account_invoice_inter_company-10.0.1.1.1.dist-info/namespace_packages.txt
odoo10_addon_account_invoice_inter_company-10.0.1.1.1.dist-info/top_level.txt
odoo10_addon_account_invoice_inter_company-10.0.1.1.1.dist-info/RECORD
